Topsis_102003592_Bhavna/Bhavna_102003592.py
Topsis_102003592_Bhavna-0.5.dist-info/Licence.txt
Topsis_102003592_Bhavna-0.5.dist-info/METADATA
Topsis_102003592_Bhavna-0.5.dist-info/WHEEL
Topsis_102003592_Bhavna-0.5.dist-info/entry_points.txt
Topsis_102003592_Bhavna-0.5.dist-info/top_level.txt
Topsis_102003592_Bhavna-0.5.dist-info/RECORD
