Metadata-Version: 2.1
Name: Topsis-102003592-Bhavna
Version: 0.5
Summary: Evaluation of alternatives based on multiple criteria using TOPSIS method.
Home-page: UNKNOWN
Author: Bhavna Goyal
Author-email: bgoyal_be20@thapar.edu
License: UNKNOWN
Platform: UNKNOWN
Classifier: Programming Language :: Python :: 3
Classifier: License :: OSI Approved :: MIT License
Classifier: Operating System :: OS Independent
Requires-Dist: pandas
